reqbuddy/__init__.py
reqbuddy/cli.py
reqbuddy/main.py
reqbuddy-0.1.9.dist-info/licenses/LICENSE
reqbuddy-0.1.9.dist-info/METADATA
reqbuddy-0.1.9.dist-info/WHEEL
reqbuddy-0.1.9.dist-info/entry_points.txt
reqbuddy-0.1.9.dist-info/top_level.txt
reqbuddy-0.1.9.dist-info/RECORD
