Metadata-Version: 2.4
Name: reqbuddy
Version: 0.1.9
Summary: Lightweight tool to extract and analyze Python requirements.
Author-email: Astin Biju <astinofficial44@gmail.com>
License: MIT
Project-URL: Homepage, https://github.com/AstinOfficial/reqbuddy
Project-URL: Source, https://github.com/AstinOfficial/reqbuddy
Project-URL: Issues, https://github.com/AstinOfficial/reqbuddy/issues
Keywords: requirements,parser,dependencies,tools,requirement finder,create requirements,build requirements,project
Classifier: Programming Language :: Python :: 3
Classifier: Programming Language :: Python :: 3.7
Classifier: Programming Language :: Python :: 3.8
Classifier: Programming Language :: Python :: 3.9
Classifier: Programming Language :: Python :: 3.10
Classifier: Programming Language :: Python :: 3.11
Classifier: Programming Language :: Python :: 3.12
Classifier: License :: OSI Approved :: MIT License
Classifier: Operating System :: OS Independent
Classifier: Intended Audience :: Developers
Classifier: Topic :: Software Development :: Libraries :: Python Modules
Requires-Python: >=3.8
License-File: LICENSE
Dynamic: license-file
